AUTHORS
CHANGELOG.txt
DESCRIPTION
LICENSE
MANIFEST.in
README.md
README.rst
requirements.txt
setup.cfg
setup.py
tox.ini
magicembed/__init__.py
magicembed/models.py
magicembed/providers.py
magicembed.egg-info/PKG-INFO
magicembed.egg-info/SOURCES.txt
magicembed.egg-info/dependency_links.txt
magicembed.egg-info/pbr.json
magicembed.egg-info/requires.txt
magicembed.egg-info/top_level.txt
magicembed/templatetags/__init__.py
magicembed/templatetags/magicembed_tags.py
magicembed/tests/.coveragerc
magicembed/tests/__init__.py
magicembed/tests/runtests.py
magicembed/tests/south_settings.py
magicembed/tests/test.py
magicembed/tests/test_settings.py
magicembed/tests/urls.py
magicembed/tests/test_app/__init__.py
magicembed/tests/test_app/models.py
magicembed/tests/test_app/templates/400.html
magicembed/tests/test_app/templates/500.html