Metadata-Version: 1.0
Name: magicembed
Version: 1.0.0
Summary: An easy and simple Django template tag and tool to embed video and get thumbnails from video providers.
